cdtea/__init__.py
cdtea/simplicial.py
cdtea/tests/__init__.py
cdtea/tests/test_simplicial.py
cdtea-0.0.2.dist-info/LICENSE
cdtea-0.0.2.dist-info/METADATA
cdtea-0.0.2.dist-info/WHEEL
cdtea-0.0.2.dist-info/top_level.txt
cdtea-0.0.2.dist-info/RECORD
