Metadata-Version: 2.1
Name: cdtea
Version: 0.0.2
Summary: CDTea
Home-page: https://github.com/JWKennington/cdtea
Author: James Kennington
Author-email: jameswkennington@gmail.com
License: MIT
Platform: UNKNOWN
Classifier: Programming Language :: Python
Classifier: Programming Language :: Python :: 3.7
Classifier: Programming Language :: Python :: 3.8
Classifier: Operating System :: MacOS
Classifier: Operating System :: POSIX :: Linux
Classifier: Operating System :: Microsoft :: Windows
Requires-Python: ==3.7, ==3.8
Requires-Dist: matplotlib
Requires-Dist: numpy
Requires-Dist: plotly
